{"name":"Teechart","tagline":"Charting and graphing javascript, node.js module and jQuery plugin","body":"TeeChart HTML5 Javascript, module for Node.js and jQuery plugin.\r\n\r\nSteema Software www.steema.com\r\n==============================\r\n\r\nCharting module using TeeChart for JavaScript.\r\nFree for non-commercial use. See license.txt.\r\n\r\nFor TeeChart Javascript demos, documentation, support:\r\n\r\nhttp://www.steema.com/teechart/html5/\r\n\r\nDependencies:\r\n-------------\r\n\r\nTo create and render a chart picture at server-side,\r\nan HTML5 <canvas> node library is required.\r\n\r\nTeeChart has been tested on Linux using node.js and\r\nnode-canvas module.\r\n\r\n\r\nInstallation:\r\n-------------\r\n\r\n-Install node.js:\r\n http://nodejs.org\r\n\r\n-Install node-canvas module:\r\n http://github.com/LearnBoost/node-canvas\r\n\r\n\r\nRunning included example:\r\n-------------------------\r\n\r\n# node main.js\r\n\r\nThis small javascript code will accept requests via web to\r\nreturn an image/png sample chart:\r\n\r\nhttp://127.0.0.1:4242\r\n\r\n\r\nNotes:\r\n------\r\n\r\nThe important bits of code are:\r\n\r\n1) Using TeeChart and node-canvas modules:\r\n\r\n  var tee=require('./lib/teechart-min.js'),\r\n      Canvas=require('./node-canvas/lib/canvas.js');\r\n\r\n2) Creating a Tee.Chart, passing the canvas:\r\n\r\n  var canvas = new Canvas(500,300),\r\n      chart = new tee.Tee.Chart(canvas);\r\n\r\n3) Manually specifying chart size (this step should not\r\n   be mandatory in future releases) :\r\n\r\n     chart.bounds.set(0,0,500,300);\r\n\r\n4) Add chart series, data, change formatting, etc, and DRAW:\r\n\r\n  chart.title.text=\"Node.js and TeeChart\";\r\n  chart.addSeries(new tee.Tee.Bar([5,3,7,1,2]));\r\n  chart.draw();\r\n\r\n5) Return the chart as image, or save it to a file, etc\r\n   (Check node-canvas documentation for more options)\r\n\r\n  res.writeHead(200, {'Content-Type': 'text/html'});\r\n  res.end(\"&lt;html&gt;&lt;body&gt;&lt;img src='\"+canvas.toDataURL()+\"'/&gt;&lt;/body&gt;&lt;/html&gt;\");\r\n\r\n\r\n","google":"UA-7504244-1","note":"Don't delete this file! It's used internally to help with page regeneration."}